LICENSE
MANIFEST.in
README.rst
setup.py
django_simple_cookie_consent/__init__.py
django_simple_cookie_consent/admin.py
django_simple_cookie_consent/apps.py
django_simple_cookie_consent/forms.py
django_simple_cookie_consent/models.py
django_simple_cookie_consent.egg-info/PKG-INFO
django_simple_cookie_consent.egg-info/SOURCES.txt
django_simple_cookie_consent.egg-info/dependency_links.txt
django_simple_cookie_consent.egg-info/top_level.txt
django_simple_cookie_consent/migrations/0001_initial.py
django_simple_cookie_consent/migrations/__init__.py
django_simple_cookie_consent/south_migrations/0001_initial.py
django_simple_cookie_consent/south_migrations/__init__.py
django_simple_cookie_consent/static/django_simple_cookie_consent/css/cookieconsent.min.css
django_simple_cookie_consent/static/django_simple_cookie_consent/js/cookieconsent.js
django_simple_cookie_consent/templates/django_simple_cookie_consent/cookie_message.html
django_simple_cookie_consent/templatetags/__init__.py
django_simple_cookie_consent/templatetags/django_simple_cookie_consent_tags.py